Workbook

Sheet Instructions
A1: MS Excel Practical Exam
A2: Total Questions: 30
A3: Difficulty Level: Medium
A4: Syllabus: Formulas, Logical Functions, Lookups, INDEX-MATCH, Pivot Tables & Charts, Data Analysis
A5: Attempt all questions using appropriate Excel tools/functions.

Sheet Sales_Data
A1: Order_ID | B1: Region | C1: Salesperson | D1: Product | E1: Quantity | F1: Unit_Price | G1: Sales_Date | H1: total | I1: gst amount
A2: 301 | B2: North | C2: Amit | D2: Laptop | E2: 2 | F2: 45000 | G2: 05-01-2025 | H2: {=E2:E7*F2:F7} -> 90000 | I2: =VLOOKUP(D2,Product_Master!$A$2:$C$4,3,FALSE*H2) -> 18 | L2: Row Labels | M2: Sum of total
A3: 302 | B3: South | C3: Riya | D3: Mobile | E3: 5 | F3: 15000 | G3: 07-01-2025 | H3: 75000 | I3: =VLOOKUP(D3,Product_Master!$A$2:$C$4,3,FALSE*H3) -> 12 | L3: Laptop | M3: 225000
A4: 303 | B4: East | C4: Kunal | D4: Tablet | E4: 3 | F4: 18000 | G4: 10-01-2025 | H4: 54000 | I4: =VLOOKUP(D4,Product_Master!$A$2:$C$4,3,FALSE*H4) -> 12 | L4: Mobile | M4: 135000
A5: 304 | B5: West | C5: Neha | D5: Laptop | E5: 1 | F5: 45000 | G5: 12-01-2025 | H5: 45000 | I5: =VLOOKUP(D5,Product_Master!$A$2:$C$4,3,FALSE*H5) -> 18 | L5: Tablet | M5: 54000
A6: 305 | B6: North | C6: Amit | D6: Mobile | E6: 4 | F6: 15000 | G6: 15-01-2025 | H6: 60000 | I6: =VLOOKUP(D6,Product_Master!$A$2:$C$4,3,FALSE*H6) -> 12 | L6: Grand Total | M6: 414000
A7: 306 | B7: South | C7: Riya | D7: Laptop | E7: 2 | F7: 45000 | G7: 18-01-2025 | H7: 90000 | I7: =VLOOKUP(D7,Product_Master!$A$2:$C$4,3,FALSE*H7) -> 18
F15: =SUM(_xlfn.ANCHORARRAY(H2)) -> 414000

Sheet Product_Master
A1: Product | B1: Category | C1: GST_% | D1: GST_%
A2: Laptop | B2: Electronics | C2: 18 | D2: =C2/100 -> 0.18
A3: Mobile | B3: Electronics | C3: 12 | D3: =C3/100 -> 0.12
A4: Tablet | B4: Electronics | C4: 12 | D4: =C4/100 -> 0.12
C6: =SUM(C2:C4) -> 42

Sheet Student_Marks
A1: Student_ID | B1: Name | C1: Maths | D1: Statistics | E1: Excel | F1: Attendance_%
A2: 1 | B2: Rahul | C2: 78 | D2: 82 | E2: 85 | F2: 92 | H2: {=((C2:E2)/300)*100} -> 26 | I2: 27.333333 | J2: 28.333333
A3: 2 | B3: Sneha | C3: 88 | D3: 91 | E3: 90 | F3: 96 | H3: {=((C3:E3)/300)*100} -> 29.333333 | I3: 30.333333 | J3: 30
A4: 3 | B4: Arjun | C4: 65 | D4: 70 | E4: 72 | F4: 85 | H4: {=((C4:E4)/300)*100} -> 21.666667 | I4: 23.333333 | J4: 24
A5: 4 | B5: Pooja | C5: 92 | D5: 89 | E5: 94 | F5: 98 | H5: {=((C5:E5)/300)*100} -> 30.666667 | I5: 29.666667 | J5: 31.333333
A6: 5 | B6: Vikas | C6: 55 | D6: 60 | E6: 58 | F6: 80 | H6: {=((C6:E6)/300)*100} -> 18.333333 | I6: 20 | J6: 19.333333
A9: Row Labels | B9: Sum of Excel
A10: Arjun | B10: 72
A11: Pooja | B11: 94
A12: Rahul | B12: 85
A13: Sneha | B13: 90
A14: Vikas | B14: 58
A15: Grand Total | B15: 399

Sheet Questions
B1: 1. Calculate Total Sales for each order (Quantity × Unit_Price). | L1: 2
A2: ans | B2: Order_ID | C2: Region | D2: Salesperson | E2: Product | F2: Quantity | G2: Unit_Price | H2: Sales_Date | I2: total sale
B3: 301 | C3: North | D3: Amit | E3: Laptop | F3: 2 | G3: 45000 | H3: 05-01-2025 | I3: =F3*G3 -> 90000
B4: 302 | C4: South | D4: Riya | E4: Mobile | F4: 5 | G4: 15000 | H4: 07-01-2025 | I4: =F4*G4 -> 75000
B5: 303 | C5: East | D5: Kunal | E5: Tablet | F5: 3 | G5: 18000 | H5: 10-01-2025 | I5: =F5*G5 -> 54000
B6: 304 | C6: West | D6: Neha | E6: Laptop | F6: 1 | G6: 45000 | H6: 12-01-2025 | I6: =F6*G6 -> 45000
B7: 305 | C7: North | D7: Amit | E7: Mobile | F7: 4 | G7: 15000 | H7: 15-01-2025 | I7: =F7*G7 -> 60000
B8: 306 | C8: South | D8: Riya | E8: Laptop | F8: 2 | G8: 45000 | H8: 18-01-2025 | I8: =F8*G8 -> 90000
B9: 2. Calculate GST Amount using VLOOKUP from Product_Master. | L9: 2
A10: ans | B10: Order_ID | C10: Region | D10: Salesperson | E10: Product | F10: Quantity | G10: Unit_Price | H10: Sales_Date | I10: gst
B11: 301 | C11: North | D11: Amit | E11: Laptop | F11: 2 | G11: 45000 | H11: 05-01-2025 | I11: =VLOOKUP(E11,Product_Master!$A$1:$D$4,4,FALSE) -> 0.18
B12: 302 | C12: South | D12: Riya | E12: Mobile | F12: 5 | G12: 15000 | H12: 07-01-2025 | I12: =VLOOKUP(E12,Product_Master!$A$1:$D$4,4,FALSE) -> 0.12
B13: 303 | C13: East | D13: Kunal | E13: Tablet | F13: 3 | G13: 18000 | H13: 10-01-2025 | I13: =VLOOKUP(E13,Product_Master!$A$1:$D$4,4,FALSE) -> 0.12
B14: 304 | C14: West | D14: Neha | E14: Laptop | F14: 1 | G14: 45000 | H14: 12-01-2025 | I14: =VLOOKUP(E14,Product_Master!$A$1:$D$4,4,FALSE) -> 0.18
B15: 305 | C15: North | D15: Amit | E15: Mobile | F15: 4 | G15: 15000 | H15: 15-01-2025 | I15: =VLOOKUP(E15,Product_Master!$A$1:$D$4,4,FALSE) -> 0.12
B16: 306 | C16: South | D16: Riya | E16: Laptop | F16: 2 | G16: 45000 | H16: 18-01-2025 | I16: =VLOOKUP(E16,Product_Master!$A$1:$D$4,4,FALSE) -> 0.18
B19: 3. Find Final Amount payable (Total Sales + GST). | L19: 2
A20: ans | B20: Order_ID | C20: Region | D20: Salesperson | E20: Product | F20: Quantity | G20: Unit_Price | H20: Sales_Date | I20: total sale | J20: gst | K20: ans
B21: 301 | C21: North | D21: Amit | E21: Laptop | F21: 2 | G21: 45000 | H21: 05-01-2025 | I21: 90000 | J21: 0.18 | K21: =I21*J21 -> 16200
B22: 302 | C22: South | D22: Riya | E22: Mobile | F22: 5 | G22: 15000 | H22: 07-01-2025 | I22: 75000 | J22: 0.12 | K22: =I22*J22 -> 9000
B23: 303 | C23: East | D23: Kunal | E23: Tablet | F23: 3 | G23: 18000 | H23: 10-01-2025 | I23: 54000 | J23: 0.12 | K23: =I23*J23 -> 6480
B24: 304 | C24: West | D24: Neha | E24: Laptop | F24: 1 | G24: 45000 | H24: 12-01-2025 | I24: 45000 | J24: 0.18 | K24: =I24*J24 -> 8100
B25: 305 | C25: North | D25: Amit | E25: Mobile | F25: 4 | G25: 15000 | H25: 15-01-2025 | I25: 60000 | J25: 0.12 | K25: =I25*J25 -> 7200
B26: 306 | C26: South | D26: Riya | E26: Laptop | F26: 2 | G26: 45000 | H26: 18-01-2025 | I26: 90000 | J26: 0.18 | K26: =I26*J26 -> 16200
B29: 4. Find Grand Total of Final Amount. | L29: 2
A30: ans | B30: total sale | C30: grand total
B31: 90000 | C31: =SUM(B31:B36) -> 414000
B32: 75000
B33: 54000
B34: 45000
B35: 60000
B36: 90000
B38: 5. Count total number of orders using COUNTA. | L38: 2
A39: ans | C39: =COUNTA(Sales_Data!A2:A7) -> 6
B41: 6. Find Region-wise total sales using SUMIF. | L41: 2
A42: ans | B42: North | C42: {=SUMIF(Questions!B42,Sales_Data!B2:B7,_xlfn.ANCHORARRAY(Sales_Data!H2))} -> 90000
C43: 0
C44: 0
C45: 0
C46: 90000
C47: 0
B49: 7. Use IF to classify Quantity as High (>3) or Low (<=3). | L49: 2
A50: ans | C50: =IF(Sales_Data!E2>3,"high",IF(Sales_Data!E2<=3,"low")) -> low
B52: 8. Find the maximum and minimum Final Amount. | L52: 2
A53: ans | B53: minimum | C53: =MIN(_xlfn.ANCHORARRAY(Sales_Data!H2)) -> 45000
B54: maximum | C54: =MAX(_xlfn.ANCHORARRAY(Sales_Data!H2)) -> 90000
B55: 9. Extract month name from Sales_Date. | L55: 2
A56: ans | C56: =TEXT(Sales_Data!G2,"mmmm") -> January
B58: 10. Sort Sales_Data by Final Amount (Descending). | L58: 2
A59: ans | C59: Order_ID | D59: Region | E59: Salesperson | F59: Product | G59: Quantity | H59: Unit_Price | I59: Sales_Date | J59: total | K59: gst amount
C60: 301 | D60: North | E60: Amit | F60: Laptop | G60: 2 | H60: 45000 | I60: 05-01-2025 | J60: 90000 | K60: 18
C61: 306 | D61: South | E61: Riya | F61: Laptop | G61: 2 | H61: 45000 | I61: 18-01-2025 | J61: 90000 | K61: 18
C62: 302 | D62: South | E62: Riya | F62: Mobile | G62: 5 | H62: 15000 | I62: 07-01-2025 | J62: 75000 | K62: 12
C63: 305 | D63: North | E63: Amit | F63: Mobile | G63: 4 | H63: 15000 | I63: 15-01-2025 | J63: 60000 | K63: 12
C64: 303 | D64: East | E64: Kunal | F64: Tablet | G64: 3 | H64: 18000 | I64: 10-01-2025 | J64: 54000 | K64: 12
C65: 304 | D65: West | E65: Neha | F65: Laptop | G65: 1 | H65: 45000 | I65: 12-01-2025 | J65: 45000 | K65: 18
B68: 11. Use INDEX-MATCH to fetch Product Category. | L68: 2
A69: ans | C69: Product | D69: category
C70: Laptop | D70: =INDEX(Product_Master!B2:B4,MATCH(Questions!C70,Product_Master!A2:A4,0)) -> Electronics
C71: Mobile | D71: =INDEX(Product_Master!B3:B5,MATCH(Questions!C71,Product_Master!A3:A5,0)) -> Electronics
C72: Tablet | D72: =INDEX(Product_Master!B4:B6,MATCH(Questions!C72,Product_Master!A4:A6,0)) -> Electronics
B74: 12. Calculate average marks of each student. | L74: 2
A75: ans | C75: Name | D75: Maths | E75: Statistics | F75: Excel | G75: avg marks
C76: Rahul | D76: 78 | E76: 82 | F76: 85 | G76: =AVERAGE(D76:F76) -> 81.666667
C77: Sneha | D77: 88 | E77: 91 | F77: 90 | G77: =AVERAGE(D77:F77) -> 89.666667
C78: Arjun | D78: 65 | E78: 70 | F78: 72 | G78: =AVERAGE(D78:F78) -> 69
C79: Pooja | D79: 92 | E79: 89 | F79: 94 | G79: =AVERAGE(D79:F79) -> 91.666667
C80: Vikas | D80: 55 | E80: 60 | F80: 58 | G80: =AVERAGE(D80:F80) -> 57.666667
B82: 13. Find the topper based on average marks. | L82: 2
A83: ans | C83: Name | D83: Maths | E83: Statistics | F83: Excel | G83: avg marks
C84: Rahul | D84: 78 | E84: 82 | F84: 85 | G84: =AVERAGE(D84:F84) -> 81.666667
C85: Sneha | D85: 88 | E85: 91 | F85: 90 | G85: =AVERAGE(D85:F85) -> 89.666667
C86: Arjun | D86: 65 | E86: 70 | F86: 72 | G86: =AVERAGE(D86:F86) -> 69
C87: Pooja | D87: 92 | E87: 89 | F87: 94 | G87: =AVERAGE(D87:F87) -> 91.666667
C88: Vikas | D88: 55 | E88: 60 | F88: 58 | G88: =AVERAGE(D88:F88) -> 57.666667
B90: 14. Count students with Attendance above 90%. | L90: 2
A91: ans
B92: Student_ID | C92: Name | D92: Maths | E92: Statistics | F92: Excel | G92: Attendance_%
B93: 1 | C93: Rahul | D93: 78 | E93: 82 | F93: 85 | G93: 92
B94: 2 | C94: Sneha | D94: 88 | E94: 91 | F94: 90 | G94: 96
B95: 3 | C95: Arjun | D95: 65 | E95: 70 | F95: 72 | G95: 85
B96: 4 | C96: Pooja | D96: 92 | E96: 89 | F96: 94 | G96: 98
B97: 5 | C97: Vikas | D97: 55 | E97: 60 | F97: 58 | G97: 80
B99: 15. Use IF to classify students as Eligible (Attendance >= 85%). | L99: 2
A100: ans
B101: Student_ID | C101: Name | D101: Maths | E101: Statistics | F101: Excel | G101: Attendance_% | I101: classify
B102: 1 | C102: Rahul | D102: 78 | E102: 82 | F102: 85 | G102: 92 | I102: =IF(G102>=85,"Eligible","not elgible") -> Eligible
B103: 2 | C103: Sneha | D103: 88 | E103: 91 | F103: 90 | G103: 96 | I103: =IF(G103>=85,"Eligible","not elgible") -> Eligible
B104: 3 | C104: Arjun | D104: 65 | E104: 70 | F104: 72 | G104: 85 | I104: =IF(G104>=85,"Eligible","not elgible") -> Eligible
B105: 4 | C105: Pooja | D105: 92 | E105: 89 | F105: 94 | G105: 98 | I105: =IF(G105>=85,"Eligible","not elgible") -> Eligible
B106: 5 | C106: Vikas | D106: 55 | E106: 60 | F106: 58 | G106: 80 | I106: =IF(G106>=85,"Eligible","not elgible") -> not elgible
B108: 16. Create a Pivot Table showing Product-wise Total Sales. | L108: 2
A109: ans | B109: Row Labels | C109: Sum of total
B110: Laptop | C110: 225000
B111: Mobile | C111: 135000
B112: Tablet | C112: 54000
B113: Grand Total | C113: 414000
B115: 17. Create a Pivot Table showing Region-wise Total Sales. | L115: 2
A116: ans | B116: Row Labels | C116: Sum of total
B117: East | C117: 54000
...
